image_scraper_tool/__init__.py
image_scraper_tool/custom_image_extractor.py
image_scraper_tool-0.1.4.dist-info/METADATA
image_scraper_tool-0.1.4.dist-info/WHEEL
image_scraper_tool-0.1.4.dist-info/entry_points.txt
image_scraper_tool-0.1.4.dist-info/top_level.txt
image_scraper_tool-0.1.4.dist-info/RECORD
